{
  "memories": [
    " -> Hi there, it's so lovely to meet you! How's your day going so far?"
  ],
  "relationships": {
    "Bob": {
      "familiarity": 127
    }
  },
  "goal": "build rapport",
  "pending_actions": [
    "say",
    "ask",
    "express",
    "confront",
    "cooperate"
  ],
  "tension_level": 20,
  "personality": "friendly",
  "name": "Alice",
  "stressful_phrases": [
    "conflict",
    "argument",
    "disagree",
    "angry",
    "disappointed",
    "rejected",
    "criticized",
    "ignored",
    "disrespected",
    "rude",
    "unfriendly",
    "hostile",
    "mean",
    "upset",
    "hurt feelings",
    "misunderstood",
    "alone",
    "isolated",
    "abandoned",
    "betrayed"
  ]
}